.gitignore
LICENSE
base_example.yml
codecov.yml
readme.md
requirements.txt
setup.cfg
setup.py
test_db
test_db.db
test_db_actions.yaml
.github/workflows/deploy_pipeline.yaml
.github/workflows/test_on_merge.yaml
.github/workflows/test_on_push.yaml
YamlBaseCache/_SQLite_test_db.yaml
src/YamlBase/__init__.py
src/YamlBase/exceptions.py
src/YamlBase/table_representation.py
src/YamlBase/utils.py
src/YamlBase/yaml_worker.py
src/YamlBase/yamlbase.py
src/YamlBase/ybase.py
src/YamlBase.egg-info/PKG-INFO
src/YamlBase.egg-info/SOURCES.txt
src/YamlBase.egg-info/dependency_links.txt
src/YamlBase.egg-info/entry_points.txt
src/YamlBase.egg-info/not-zip-safe
src/YamlBase.egg-info/requires.txt
src/YamlBase.egg-info/top_level.txt
src/YamlBase/dbworkers/__init__.py
src/YamlBase/dbworkers/base.py
src/YamlBase/dbworkers/postgre_worker.py
src/YamlBase/dbworkers/sqlite_worker.py
src/YamlBase/sql/__init__.py
src/YamlBase/sql/postgre.py
src/YamlBase/sql/sql.py
src/YamlBase/sql/sqlite.py
test/conftest.py
test/test_Postgreworker.py
test/test_SQLite.py
test/test_SqliteWorker.py
test/test_TableColumn.py
test/test_base.yml
test/test_base_postgre.yml
test/test_db
test/test_db_actions.yaml
test/test_pipeline.py
test/test_postgresql.py
test/test_utils.py
test/test_yamlworker.py
test/test_ybase.py
test/configs_for_tests/test_base_pipeline.yaml
test/configs_for_tests/test_db_actions.yaml
test/configs_for_tests/test_actions/test_db_actions.yaml
test/configs_for_tests/test_no_fields/test_no_db_type.yml
test/configs_for_tests/test_no_fields/test_no_dbname.yml
test/configs_for_tests/test_no_fields/test_no_ip.yml
test/configs_for_tests/test_no_fields/test_no_password.yml
test/configs_for_tests/test_no_fields/test_no_username.yml
test/configs_for_tests/test_ybase/test_db_actions.yaml
test/configs_for_tests/test_ybase/test_miss_db_type.yml